RangleSAngular2TrainingBookZhongwenban/README.md
RangleSAngular2TrainingBookZhongwenban/__init__.py
RangleSAngular2TrainingBookZhongwenban/__main__.py
RangleSAngular2TrainingBookZhongwenban/file.epub
RangleSAngular2TrainingBookZhongwenban/index.html
RangleSAngular2TrainingBookZhongwenban/css/__init__.py
RangleSAngular2TrainingBookZhongwenban/css/annotations.css
RangleSAngular2TrainingBookZhongwenban/css/main.css
RangleSAngular2TrainingBookZhongwenban/css/normalize.css
RangleSAngular2TrainingBookZhongwenban/css/popup.css
RangleSAngular2TrainingBookZhongwenban/font/__init__.py
RangleSAngular2TrainingBookZhongwenban/font/fontello.eot
RangleSAngular2TrainingBookZhongwenban/font/fontello.svg
RangleSAngular2TrainingBookZhongwenban/font/fontello.ttf
RangleSAngular2TrainingBookZhongwenban/font/fontello.woff
RangleSAngular2TrainingBookZhongwenban/img/__init__.py
RangleSAngular2TrainingBookZhongwenban/img/annotator-glyph-sprite.png
RangleSAngular2TrainingBookZhongwenban/img/annotator-icon-sprite.png
RangleSAngular2TrainingBookZhongwenban/img/apple-touch-icon.png
RangleSAngular2TrainingBookZhongwenban/img/cancelfullscreen.png
RangleSAngular2TrainingBookZhongwenban/img/close.png
RangleSAngular2TrainingBookZhongwenban/img/fullscreen.png
RangleSAngular2TrainingBookZhongwenban/img/loader.gif
RangleSAngular2TrainingBookZhongwenban/img/menu-icon.png
RangleSAngular2TrainingBookZhongwenban/img/save.png
RangleSAngular2TrainingBookZhongwenban/img/saved.png
RangleSAngular2TrainingBookZhongwenban/img/settings-s.png
RangleSAngular2TrainingBookZhongwenban/img/settings.png
RangleSAngular2TrainingBookZhongwenban/img/star.png
RangleSAngular2TrainingBookZhongwenban/js/__init__.py
RangleSAngular2TrainingBookZhongwenban/js/epub.js
RangleSAngular2TrainingBookZhongwenban/js/epub.min.js
RangleSAngular2TrainingBookZhongwenban/js/epub.min.map
RangleSAngular2TrainingBookZhongwenban/js/hooks.min.js
RangleSAngular2TrainingBookZhongwenban/js/hooks.min.map
rangle_s_angular_2_training_book_zhongwenban-2024.3.4.0.dist-info/METADATA
rangle_s_angular_2_training_book_zhongwenban-2024.3.4.0.dist-info/WHEEL
rangle_s_angular_2_training_book_zhongwenban-2024.3.4.0.dist-info/entry_points.txt
rangle_s_angular_2_training_book_zhongwenban-2024.3.4.0.dist-info/top_level.txt
rangle_s_angular_2_training_book_zhongwenban-2024.3.4.0.dist-info/RECORD
